jupyter_server_proxy/__init__.py
jupyter_server_proxy/_version.py
jupyter_server_proxy/api.py
jupyter_server_proxy/config.py
jupyter_server_proxy/handlers.py
jupyter_server_proxy/unixsock.py
jupyter_server_proxy/utils.py
jupyter_server_proxy/websocket.py
jupyter_server_proxy/etc/jupyter_notebook_config.d/jupyter-server-proxy.json
jupyter_server_proxy/etc/jupyter_server_config.d/jupyter-server-proxy.json
jupyter_server_proxy/etc/nbconfig/tree.d/jupyter-server-proxy.json
jupyter_server_proxy/static/tree.js
jupyter_server_proxy-4.1.1.data/data/etc/jupyter/jupyter_notebook_config.d/jupyter-server-proxy.json
jupyter_server_proxy-4.1.1.data/data/etc/jupyter/jupyter_server_config.d/jupyter-server-proxy.json
jupyter_server_proxy-4.1.1.data/data/etc/jupyter/nbconfig/tree.d/jupyter-server-proxy.json
jupyter_server_proxy-4.1.1.data/data/share/jupyter/nbextensions/jupyter_server_proxy/tree.js
jupyter_server_proxy-4.1.1.data/data/share/jupyter/labextensions/@jupyterhub/jupyter-server-proxy/package.json
jupyter_server_proxy-4.1.1.data/data/share/jupyter/labextensions/@jupyterhub/jupyter-server-proxy/static/961.5a30de36bec162032e99.js
jupyter_server_proxy-4.1.1.data/data/share/jupyter/labextensions/@jupyterhub/jupyter-server-proxy/static/remoteEntry.702d470ad13e64bbc709.js
jupyter_server_proxy-4.1.1.data/data/share/jupyter/labextensions/@jupyterhub/jupyter-server-proxy/static/style.js
jupyter_server_proxy-4.1.1.data/data/share/jupyter/labextensions/@jupyterhub/jupyter-server-proxy/static/third-party-licenses.json
jupyter_server_proxy-4.1.1.dist-info/METADATA
jupyter_server_proxy-4.1.1.dist-info/WHEEL
jupyter_server_proxy-4.1.1.dist-info/licenses/LICENSE
jupyter_server_proxy-4.1.1.dist-info/RECORD
