Metadata-Version: 2.1
Name: jupyter_server_proxy
Version: 4.1.1
Summary: A Jupyter server extension to run additional processes and proxy to them that comes bundled JupyterLab extension to launch pre-defined processes.
Project-URL: Documentation, https://jupyter-server-proxy.readthedocs.io
Project-URL: Source, https://github.com/jupyterhub/jupyter-server-proxy
Project-URL: Tracker, https://github.com/jupyterhub/jupyter-server-proxy/issues
Author-email: Ryan Lovett <rylo@berkeley.edu>, Yuvi Panda <yuvipanda@gmail.com>, Jupyter Development Team <jupyter@googlegroups.com>
License: BSD 3-Clause License
License-File: LICENSE
Keywords: jupyter,jupyterlab,jupyterlab-extension
Classifier: Framework :: Jupyter
Classifier: Framework :: Jupyter :: JupyterLab
Classifier: Framework :: Jupyter :: JupyterLab :: 3
Classifier: Framework :: Jupyter :: JupyterLab :: 4
Classifier: Framework :: Jupyter :: JupyterLab :: Extensions
Classifier: Framework :: Jupyter :: JupyterLab :: Extensions :: Prebuilt
Classifier: License :: OSI Approved :: BSD License
Classifier: Operating System :: MacOS :: MacOS X
Classifier: Operating System :: Microsoft :: Windows
Classifier: Operating System :: POSIX :: Linux
Classifier: Programming Language :: Python
Classifier: Programming Language :: Python :: 3
Classifier: Programming Language :: Python :: 3.8
Classifier: Programming Language :: Python :: 3.9
Classifier: Programming Language :: Python :: 3.10
Classifier: Programming Language :: Python :: 3.11
Requires-Python: >=3.8
Requires-Dist: aiohttp
Requires-Dist: importlib-metadata>=4.8.3; python_version < '3.10'
Requires-Dist: jupyter-server>=1.0
Requires-Dist: simpervisor>=1.0
Requires-Dist: tornado>=5.1
Requires-Dist: traitlets>=4.2.1
Provides-Extra: acceptance
Requires-Dist: jupyter-server-proxy[test]; extra == 'acceptance'
Requires-Dist: robotframework-jupyterlibrary>=0.4.2; extra == 'acceptance'
Provides-Extra: classic
Requires-Dist: jupyter-server<2; extra == 'classic'
Requires-Dist: jupyterlab<4.0.0a0,>=3.0.0; extra == 'classic'
Requires-Dist: notebook<7.0.0a0; extra == 'classic'
Provides-Extra: lab
Requires-Dist: jupyter-server>=2; extra == 'lab'
Requires-Dist: jupyterlab<5.0.0a0,>=4.0.5; extra == 'lab'
Requires-Dist: nbclassic; extra == 'lab'
Requires-Dist: notebook>=7; extra == 'lab'
Provides-Extra: test
Requires-Dist: pytest; extra == 'test'
Requires-Dist: pytest-asyncio; extra == 'test'
Requires-Dist: pytest-cov; extra == 'test'
Requires-Dist: pytest-html; extra == 'test'
